prequ/__init__.py
prequ/__main__.py
prequ/_compat.py
prequ/_log_utils.py
prequ/_pip_compat.py
prequ/cache.py
prequ/configuration.py
prequ/exceptions.py
prequ/file_replacer.py
prequ/ini_parser.py
prequ/locations.py
prequ/logging.py
prequ/resolver.py
prequ/sync.py
prequ/utils.py
prequ/writer.py
prequ/repositories/__init__.py
prequ/repositories/base.py
prequ/repositories/local.py
prequ/repositories/pypi.py
prequ/scripts/__init__.py
prequ/scripts/_repo.py
prequ/scripts/build_wheels.py
prequ/scripts/check.py
prequ/scripts/compile.py
prequ/scripts/compile_in.py
prequ/scripts/prequ.py
prequ/scripts/sync.py
prequ/scripts/update.py
prequ-1.4.7.dist-info/LICENSE
prequ-1.4.7.dist-info/METADATA
prequ-1.4.7.dist-info/WHEEL
prequ-1.4.7.dist-info/entry_points.txt
prequ-1.4.7.dist-info/top_level.txt
prequ-1.4.7.dist-info/RECORD
